CribbageSim/CribbageBoard.py
CribbageSim/CribbageCombination.py
CribbageSim/CribbageDeal.py
CribbageSim/CribbageGame.py
CribbageSim/CribbageGameOutputEvents.py
CribbageSim/CribbagePlayStrategy.py
CribbageSim/CribbageSimulator.py
CribbageSim/__init__.py
CribbageSim/exceptions.py
CribbageSim/main.py
cribbagesim-1.0.2.dist-info/METADATA
cribbagesim-1.0.2.dist-info/WHEEL
cribbagesim-1.0.2.dist-info/entry_points.txt
cribbagesim-1.0.2.dist-info/licenses/LICENSE
cribbagesim-1.0.2.dist-info/RECORD
