Metadata-Version: 2.4
Name: CribbageSim
Version: 1.0.2
Summary: CribbageSim is a Cribbage card game simulator that can be played interactively or automatically to generate game-play statistics.
Keywords: console,desktop,simulator,cribbage,game
Author-Email: "Kevin R. Geurts" <kevin.r.geurts@gmail.com>
License-Expression: MIT
License-File: LICENSE
Classifier: Programming Language :: Python :: 3
Classifier: Operating System :: OS Independent
Classifier: Development Status :: 5 - Production/Stable
Classifier: Environment :: Console
Classifier: Intended Audience :: End Users/Desktop
Classifier: Topic :: Games/Entertainment :: Turn Based Strategy
Project-URL: Homepage, https://github.com/KevinRGeurts/CribbageSim
Project-URL: Issues, https://github.com/KevinRGeurts/CribbageSim/issues
Requires-Python: >=3.12
Requires-Dist: UserResponseCollector>=1.1.0
Requires-Dist: HandsDecksCards>=1.0.0
